source/header.vh
`define OPCODE_WIDTH 6
`define RTYPE 0
`define LOAD 1
`define STORE 2
`define BEQ 3
`define ADDI 4
`define ADDIU 5
`define SLTI 6
`define SLTIU 7
`define ANDI 8
`define ORI 9
`define XORI 10
`define BNE 11

`define FUNCT_WIDTH 6
`define ADD 6'b100000
`define SUB 6'b100001
`define AND 6'b100010
`define OR 6'b100011
`define XOR 6'b100100
`define SLT 6'b100101
`define SLTU 6'b100110
`define SLL 6'b100111
`define SRL 6'b101000
`define SRA 6'b101001
`define EQ 6'b101010
`define NEQ 6'b101011
`define GE 6'b101100
`define GEU 6'b101101

source/decoder.v
`ifndef DECODER_V
`define DECODER_V
`include "./source/header.vh"
module decode #(
    parameter AWIDTH = 5,
    parameter IWIDTH = 32, 
    parameter DWIDTH = 32,
    parameter IMM_WIDTH = 16
)(
    d_clk, d_rst, d_i_ce, d_i_instr, d_o_opcode, d_o_funct, d_o_addr_rs, d_o_addr_rt,
    d_o_addr_rd, d_o_imm, d_o_ce
);
    input d_clk, d_rst;
    input [IWIDTH - 1 : 0] d_i_instr;
    input d_i_ce;
    output reg [AWIDTH - 1 : 0] d_o_addr_rs, d_o_addr_rt, d_o_addr_rd;
    output reg [`OPCODE_WIDTH - 1 : 0] d_o_opcode;
    output reg [`FUNCT_WIDTH - 1 : 0] d_o_funct;
    output reg [IMM_WIDTH - 1 : 0] d_o_imm;
    output reg d_o_ce;

    wire [DWIDTH - 1 : 0] d_i_data_rs, d_i_data_rt;

    wire [`OPCODE_WIDTH - 1 : 0] d_i_opcode = d_i_instr[31 : 26];
    wire [`FUNCT_WIDTH - 1 : 0] d_i_funct = d_i_instr[5 : 0];

    wire op_rtype = d_i_opcode == `RTYPE;
    wire op_load = d_i_opcode == `LOAD;
    wire op_store = d_i_opcode == `STORE;
    wire op_beq = d_i_opcode == `BEQ;
    wire op_bne = d_i_opcode == `BNE;
    wire op_addi = d_i_opcode == `ADDI;
    wire op_addiu = d_i_opcode == `ADDIU;
    wire op_slti = d_i_opcode == `SLTI;
    wire op_sltiu = d_i_opcode == `SLTIU;
    wire op_andi = d_i_opcode == `ANDI;
    wire op_ori = d_i_opcode == `ORI;
    wire op_xori = d_i_opcode == `XORI;
    
    wire funct_add = d_i_funct == `ADD;
    wire funct_sub = d_i_funct == `SUB;
    wire funct_and = d_i_funct == `AND;
    wire funct_or = d_i_funct == `OR;
    wire funct_xor = d_i_funct == `XOR;
    wire [4 : 0] rs, rt, rd;
    wire [`OPCODE_WIDTH - 1 : 0] opcode;
    wire [`FUNCT_WIDTH - 1 : 0] funct; 
    wire [IMM_WIDTH - 1 : 0] imm;
    assign rs = d_i_instr[25 : 21];
    assign rt = d_i_instr[20 : 16];
    assign rd = d_i_instr[15 : 11];
    assign opcode = d_i_instr[31 : 26];
    assign funct = d_i_instr[5 : 0];
    assign imm = d_i_instr[15 : 0];
    always @(posedge d_clk, negedge d_rst) begin
        if (!d_rst) begin
            d_o_addr_rs <= {AWIDTH{1'b0}};
            d_o_addr_rt <= {AWIDTH{1'b0}};
            d_o_addr_rd <= {AWIDTH{1'b0}};
            d_o_opcode <= {`OPCODE_WIDTH{1'b0}};
            d_o_funct <= {`FUNCT_WIDTH{1'b0}};
            d_o_imm <= {DWIDTH{1'b0}};
            d_o_ce <= 1'b0;
        end 
        else begin
            if (d_i_ce) begin
                if (op_rtype) begin
                    d_o_addr_rs <= rs;
                    d_o_addr_rt <= rt;
                    d_o_addr_rd <= rd;
                    d_o_opcode <= opcode;
                    d_o_funct <= funct;
                    d_o_imm <= {DWIDTH{1'b0}};
                    d_o_ce <= 1'b1;
                end
                else if (op_load || op_store) begin
                    d_o_addr_rs <= rs;
                    d_o_addr_rt <= rt;
                    d_o_addr_rd <= {AWIDTH{1'b0}};
                    d_o_opcode <= opcode;
                    d_o_funct <= {`FUNCT_WIDTH{1'b0}};
                    d_o_imm <= imm;
                    d_o_ce <= 1'b1;
                end
                else if (op_beq || op_bne) begin
                    d_o_addr_rs <= rs;
                    d_o_addr_rt <= rt;
                    d_o_addr_rd <= {AWIDTH{1'b0}};
                    d_o_opcode <= opcode;
                    d_o_funct <= {`FUNCT_WIDTH{1'b0}};
                    d_o_imm <= imm;
                    d_o_ce <= 1'b1;
                end
                else if (op_addi || op_addiu || op_slti || op_sltiu || op_andi || op_ori || op_xori) begin
                    d_o_addr_rs <= rs;
                    d_o_addr_rt <= rt;
                    d_o_addr_rd <= {AWIDTH{1'b0}};
                    d_o_opcode <= opcode;
                    d_o_funct <= {`FUNCT_WIDTH{1'b0}};
                    d_o_imm <= imm;
                    d_o_ce <= 1'b1;
                end
                else begin
                    d_o_addr_rs <= {AWIDTH{1'b0}};
                    d_o_addr_rt <= {AWIDTH{1'b0}};
                    d_o_addr_rd <= {AWIDTH{1'b0}};
                    d_o_opcode <= {`OPCODE_WIDTH{1'b0}};
                    d_o_funct <= {`FUNCT_WIDTH{1'b0}};
                    d_o_imm <= {IMM_WIDTH{1'b0}};
                    d_o_ce <= 1'b0;
                end
            end
            else begin
                d_o_addr_rs <= {AWIDTH{1'b0}};
                d_o_addr_rt <= {AWIDTH{1'b0}};
                d_o_addr_rd <= {AWIDTH{1'b0}};
                d_o_opcode <= {`OPCODE_WIDTH{1'b0}};
                d_o_funct <= {`FUNCT_WIDTH{1'b0}};
                d_o_imm <= {DWIDTH{1'b0}};
                d_o_ce <= 1'b0;
            end
        end
    end
endmodule
`endif

test/tb_decoder.v
`timescale 1ns/1ps
`include "./source/decoder.v"

module tb_decoder;
    parameter AWIDTH = 5;
    parameter IWIDTH = 32; 
    parameter DWIDTH = 32;
    parameter IMM_WIDTH = 16;

    reg d_clk, d_rst;
    reg d_i_ce;
    reg [IWIDTH - 1 : 0] d_i_instr;
    reg [DWIDTH - 1 : 0] d_i_data_rd;
    wire [`OPCODE_WIDTH - 1 : 0] d_o_opcode;
    wire [`FUNCT_WIDTH  - 1 : 0] d_o_funct;
    wire [AWIDTH - 1 : 0] d_o_addr_rs, d_o_addr_rt;
    wire [AWIDTH - 1 : 0] d_o_addr_rd;
    wire [DWIDTH - 1 : 0] d_o_data_rs, d_o_data_rt;
    wire [IMM_WIDTH - 1 : 0] d_o_imm;
    wire d_i_wr_reg;

    // Instantiate decoder
    decode #(
        .AWIDTH(AWIDTH),
        .DWIDTH(DWIDTH),
        .IWIDTH(IWIDTH)
    ) dut (
        .d_clk(d_clk), 
        .d_rst(d_rst), 
        .d_i_ce(d_i_ce), 
        .d_i_instr(d_i_instr), 
        .d_o_opcode(d_o_opcode), 
        .d_o_funct(d_o_funct), 
        .d_o_addr_rs(d_o_addr_rs), 
        .d_o_addr_rt(d_o_addr_rt),
        .d_o_addr_rd(d_o_addr_rd), 
        .d_o_imm(d_o_imm), 
        .d_o_ce(d_o_ce)
    );

    // Clock
    initial d_clk = 0;
    always #5 d_clk = ~d_clk;

    initial begin
        $dumpfile("./waveform/decoder.vcd");
        $dumpvars(0, tb_decoder);
    end

    // Reset task
    task reset(input integer cycles);
        begin
            d_rst = 1'b0;
            repeat(cycles) @(posedge d_clk);
            d_rst = 1'b1;
            @(posedge d_clk);
        end
    endtask

    // Main test sequence
    initial begin
        d_i_ce     = 0;
        d_i_instr  = 32'h00000000;
        d_i_data_rd = 32'h00000000;

        reset(2);
        d_i_ce = 1;

        // Load 5 instructions
        @(posedge d_clk) d_i_instr = 32'h00430820; // ADD $1,$2,$3
        @(posedge d_clk) d_i_instr = 32'h00A62021; // SUB $4,$5,$6
        @(posedge d_clk) d_i_instr = 32'h01093822; // AND $7,$8,$9
        @(posedge d_clk) d_i_instr = 32'h016C5023; // OR  $10,$11,$12
        @(posedge d_clk) d_i_instr = 32'h01CF6824; // XOR $13,$14,$15
        @(posedge d_clk) d_i_instr = 32'h10410064; //ADDI $1, $2, 100

        // Thêm vài chu kỳ để quan sát output
        repeat(5) @(posedge d_clk);

        $finish;
    end

    // Monitor outputs
    initial begin
        $display("Time\t Instr\t\tOpcode\tFunct\tRS\tRT\tRD\tIMM");
        $monitor("%0t\t%h\t%0d\t%0b\t%0d\t%0d\t%0d\t%0d",
                  $time, d_i_instr, d_o_opcode, d_o_funct, 
                  dut.d_o_addr_rs, dut.d_o_addr_rt, d_o_addr_rd, d_o_imm);
    end
endmodule

waveform/decoder.vcd
$date
	Tue Oct 07 19:13:41 2025
$end
$version
	Icarus Verilog
$end
$timescale
	1ps
$end
$scope module tb_decoder $end
$var wire 5 ! d_o_addr_rd [4:0] $end
$var wire 5 " d_o_addr_rs [4:0] $end
$var wire 5 # d_o_addr_rt [4:0] $end
$var wire 1 $ d_o_ce $end
$var wire 6 % d_o_funct [5:0] $end
$var wire 16 & d_o_imm [15:0] $end
$var wire 6 ' d_o_opcode [5:0] $end
$var reg 1 ( d_clk $end
$var reg 1 ) d_i_ce $end
$var reg 32 * d_i_data_rd [31:0] $end
$var reg 32 + d_i_instr [31:0] $end
$var reg 1 , d_rst $end
$scope module dut $end
$var wire 1 - d_clk $end
$var wire 1 . d_i_ce $end
$var wire 6 / d_i_funct [5:0] $end
$var wire 32 0 d_i_instr [31:0] $end
$var wire 6 1 d_i_opcode [5:0] $end
$var wire 1 2 d_rst $end
$var wire 6 3 funct [5:0] $end
$var wire 1 4 funct_add $end
$var wire 1 5 funct_and $end
$var wire 1 6 funct_or $end
$var wire 1 7 funct_sub $end
$var wire 1 8 funct_xor $end
$var wire 16 9 imm [15:0] $end
$var wire 1 : op_addi $end
$var wire 1 ; op_addiu $end
$var wire 1 < op_andi $end
$var wire 1 = op_beq $end
$var wire 1 > op_bne $end
$var wire 1 ? op_load $end
$var wire 1 @ op_ori $end
$var wire 1 A op_rtype $end
$var wire 1 B op_slti $end
$var wire 1 C op_sltiu $end
$var wire 1 D op_store $end
$var wire 1 E op_xori $end
$var wire 6 F opcode [5:0] $end
$var wire 5 G rd [4:0] $end
$var wire 5 H rs [4:0] $end
$var wire 5 I rt [4:0] $end
$var reg 5 J d_o_addr_rd [4:0] $end
$var reg 5 K d_o_addr_rs [4:0] $end
$var reg 5 L d_o_addr_rt [4:0] $end
$var reg 1 M d_o_ce $end
$var reg 6 N d_o_funct [5:0] $end
$var reg 16 O d_o_imm [15:0] $end
$var reg 6 P d_o_opcode [5:0] $end
$upscope $end
$scope task reset $end
$var integer 32 Q cycles [31:0] $end
$upscope $end
$upscope $end
$enddefinitions $end
#0
$dumpvars
b10 Q
b0 P
b0 O
b0 N
0M
b0 L
b0 K
b0 J
b0 I
b0 H
b0 G
b0 F
0E
0D
0C
0B
1A
0@
0?
0>
0=
0<
0;
0:
b0 9
08
07
06
05
04
b0 3
02
b0 1
b0 0
b0 /
0.
0-
0,
b0 +
b0 *
0)
0(
b0 '
b0 &
b0 %
0$
b0 #
b0 "
b0 !
$end
#5000
1(
1-
#10000
0(
0-
#15000
1,
12
1(
1-
#20000
0(
0-
#25000
1M
1$
1)
1.
1(
1-
#30000
0(
0-
#35000
14
b100000 /
b10 H
b11 I
b1 G
b100000 3
b100000100000 9
b10000110000100000100000 +
b10000110000100000100000 0
1(
1-
#40000
0(
0-
#45000
b100000 N
b100000 %
b1 J
b1 !
b11 L
b11 #
b10 K
b10 "
04
17
b100001 /
b101 H
b110 I
b100 G
b100001 3
b10000000100001 9
b101001100010000000100001 +
b101001100010000000100001 0
1(
1-
#50000
0(
0-
#55000
b100001 N
b100001 %
b100 J
b100 !
b110 L
b110 #
b101 K
b101 "
07
15
b100010 /
b1000 H
b1001 I
b111 G
b100010 3
b11100000100010 9
b1000010010011100000100010 +
b1000010010011100000100010 0
1(
1-
#60000
0(
0-
#65000
b100010 N
b100010 %
b111 J
b111 !
b1001 L
b1001 #
b1000 K
b1000 "
05
16
b100011 /
b1011 H
b1100 I
b1010 G
b100011 3
b101000000100011 9
b1011011000101000000100011 +
b1011011000101000000100011 0
1(
1-
#70000
0(
0-
#75000
b100011 N
b100011 %
b1010 J
b1010 !
b1100 L
b1100 #
b1011 K
b1011 "
06
18
b100100 /
b1110 H
b1111 I
b1101 G
b100100 3
b110100000100100 9
b1110011110110100000100100 +
b1110011110110100000100100 0
1(
1-
#80000
0(
0-
#85000
b100100 N
b100100 %
b1101 J
b1101 !
b1111 L
b1111 #
b1110 K
b1110 "
0A
1:
b100 1
b10 H
b1 I
b0 G
b100 F
b1100100 9
b10000010000010000000001100100 +
b10000010000010000000001100100 0
1(
1-
#90000
0(
0-
#95000
b1100100 O
b1100100 &
b0 N
b0 %
b100 P
b100 '
b0 J
b0 !
b1 L
b1 #
b10 K
b10 "
1(
1-
