source/header.vh
`define OPCODE_WIDTH 6
`define RTYPE 0
`define LOAD 6'h23
`define STORE 6'h2b
`define BEQ 6'h4
`define BNE 6'h5
`define ADDI 6'h8
`define ADDIU 6'h9
`define SLTI 6'ha
`define SLTIU 6'hb
`define ANDI 6'hc
`define ORI 6'hd

`define FUNCT_WIDTH 6
`define ADD 6'b100000
`define SUB 6'b100010
`define AND 6'b100100
`define OR 6'b100101
`define NOR 6'b100111
`define SLT 6'b101010
`define SLTU 6'b101011
`define SLL 6'b000000
`define SRL 6'b000010
`define SRA 6'b101001
`define EQ 6'b001100
`define NEQ 6'b001101
`define GE 6'b101100
`define GEU 6'b101101
`define ADDU 6'b100001

`define DWIDTH 32
`define IWIDTH 32
`define AWIDTH 5
`define PC_WIDTH 32
`define AWIDTH_MEM 32
`define IMM_WIDTH 16
`define ALU_CONTROL 5
`define DEPTH 1

source/transmit.v
`ifndef TRANSMIT_V
`define TRANSMIT_V
`include "./source/header.vh"
module transmit (
    t_clk, t_rst, t_i_syn, t_o_instr, t_o_last, t_o_ack
);
    input t_clk, t_rst;
    input t_i_syn;
    output reg [`IWIDTH - 1 : 0] t_o_instr;
    output reg t_o_last, t_o_ack;
    integer counter;

    reg [`IWIDTH - 1 : 0] mem_instr [0 : `DEPTH - 1];

    always @(posedge t_clk, negedge t_rst) begin
        if (!t_rst) begin   
            $readmemh("./source/instr.txt", mem_instr, 0, `DEPTH - 1);
            counter <= 0;
            t_o_last <= 1'b0;
            t_o_instr <= {`IWIDTH{1'bz}};
            t_o_ack <= 1'b0;
        end
        else begin
            if (t_i_syn) begin
                t_o_instr <= mem_instr[counter];
                if (`DEPTH == 1) begin
                    t_o_last <= 1'b1;
                end
                else if (`DEPTH > 1) begin
                    t_o_last <= (counter == `DEPTH - 1) ? 1'b1 : 1'b0;
                end
                else begin
                    t_o_last <= 1'b0;
                end
                counter <= (counter < `DEPTH - 1) ? counter + 1 : 0;
                t_o_ack <= 1'b1;
                if (t_o_last) begin
                    t_o_ack <= 1'b0;
                end
            end
            else begin
                t_o_ack <= 1'b0;
                t_o_last <= 1'b0;
            end
        end
    end 
endmodule

`endif

source/instruction_fetch.v
`ifndef INSTRUCTION_FETCH_V
`define INSTRUCTION_FETCH_V
`include "./source/transmit.v"

module instruction_fetch #(
    parameter PC_WIDTH = 32,
    parameter IWIDTH = 32,
    parameter DEPTH = 5
)(
    f_clk, f_rst, f_i_ce, f_o_instr, f_o_pc, f_o_ce, f_o_valid
);
    input f_clk, f_rst;
    input f_i_ce;
    output reg [IWIDTH - 1 : 0] f_o_instr;
    output reg [PC_WIDTH - 1 : 0] f_o_pc;
    output reg f_o_ce;
    output reg f_o_valid;
    wire [IWIDTH - 1 : 0] f_i_instr;
    wire f_i_ack;
    wire f_i_last;
    reg f_o_syn;

    transmit #(
        .IWIDTH(IWIDTH),
        .DEPTH(DEPTH)
    ) t (
        .t_clk(f_clk), 
        .t_rst(f_rst), 
        .t_i_syn(f_o_syn), 
        .t_o_instr(f_i_instr), 
        .t_o_last(f_i_last), 
        .t_o_ack(f_i_ack)
    );

    always@(posedge f_clk, negedge f_rst) begin
        if (!f_rst) begin
            f_o_instr <= {IWIDTH{1'b0}};
            f_o_pc <= {PC_WIDTH{1'b0}};
            f_o_syn <= 1'b0;
            f_o_ce <= 1'b0;
            f_o_valid <= 1'b0;
        end
        else begin
            if (f_i_ce) begin
                if (f_i_ack) begin
                    f_o_instr <= f_i_instr;
                    f_o_pc <= f_o_pc + 4;
                    f_o_ce <= 1'b1;
                    f_o_valid <= 1'b1;
                end
                f_o_syn <= (f_i_last && f_i_ack) ? 1'b0 : 1'b1;
            end
            else begin
                f_o_valid <= 1'b0;
                f_o_ce <= 1'b0;
                f_o_syn <= 1'b0;
                f_o_instr <= {IWIDTH{1'b0}};
                f_o_pc <= {PC_WIDTH{1'b0}};
            end
        end
    end
endmodule
`endif

test/tb_fetch.v
`include "./source/instruction_fetch.v"
module tb;
    parameter IWIDTH = 32;
    parameter PC_WIDTH = 32;
    parameter DEPTH = 5;
    
    reg f_clk, f_rst;
    reg f_i_ce;
    wire [IWIDTH - 1 : 0] f_o_instr;
    wire [PC_WIDTH - 1 : 0] f_o_pc; 
    wire f_o_ce;
    wire f_o_valid;
    integer i;

    instruction_fetch #(
        .IWIDTH(IWIDTH),
        .DEPTH(DEPTH),
        .PC_WIDTH(PC_WIDTH)
    ) f (
        .f_clk(f_clk), 
        .f_rst(f_rst), 
        .f_i_ce(f_i_ce), 
        .f_o_instr(f_o_instr), 
        .f_o_pc(f_o_pc),
        .f_o_ce(f_o_ce),
        .f_o_valid(f_o_valid)
    );

    initial begin
        f_clk = 1'b0;
    end
    always #5 f_clk = ~f_clk;

    initial begin
        $dumpfile("./waveform/fetch.vcd");
        $dumpvars(0, tb);
    end

    task reset (input integer counter);
        begin
            f_rst = 1'b0;
            repeat(counter) @(posedge f_clk);
            f_rst = 1'b1;
        end
    endtask 

    task display (input integer counter);
        begin
            f_i_ce = 1'b1;
            for (i = 0; i < counter; i = i + 1) begin
                @(posedge f_clk);
                $display($time, " ", "instr = %h, pc = %d, last = %b, syn = %b, ack = %b, ce = %b, valid = %b", f_o_instr, f_o_pc, f.f_i_last, f.f_o_syn, f.f_i_ack, f_o_ce, f_o_valid); 
            end
            f_i_ce = 1'b0;
        end
    endtask

    initial begin
        reset(2);
        display(7);
        repeat(10) @(posedge f_clk);
        $finish;
    end
endmodule

waveform/fetch.vcd
$date
	Sun Oct 05 02:05:39 2025
$end
$version
	Icarus Verilog
$end
$timescale
	1s
$end
$scope module tb $end
$var wire 1 ! f_o_ce $end
$var wire 32 " f_o_instr [31:0] $end
$var wire 32 # f_o_pc [31:0] $end
$var wire 1 $ f_o_valid $end
$var reg 1 % f_clk $end
$var reg 1 & f_i_ce $end
$var reg 1 ' f_rst $end
$var integer 32 ( i [31:0] $end
$scope module f $end
$var wire 1 ) f_clk $end
$var wire 1 * f_i_ack $end
$var wire 1 + f_i_ce $end
$var wire 32 , f_i_instr [31:0] $end
$var wire 1 - f_i_last $end
$var wire 1 . f_rst $end
$var reg 1 / f_o_ce $end
$var reg 32 0 f_o_instr [31:0] $end
$var reg 32 1 f_o_pc [31:0] $end
$var reg 1 2 f_o_syn $end
$var reg 1 3 f_o_valid $end
$scope module t $end
$var wire 1 ) t_clk $end
$var wire 1 4 t_i_syn $end
$var wire 1 . t_rst $end
$var integer 32 5 counter [31:0] $end
$var reg 1 6 t_o_ack $end
$var reg 32 7 t_o_instr [31:0] $end
$var reg 1 8 t_o_last $end
$upscope $end
$upscope $end
$scope task display $end
$var integer 32 9 counter [31:0] $end
$upscope $end
$scope task reset $end
$var integer 32 : counter [31:0] $end
$upscope $end
$upscope $end
$enddefinitions $end
#0
$dumpvars
b10 :
bx 9
08
b0 7
06
b0 5
04
03
02
b0 1
b0 0
0/
0.
0-
b0 ,
x+
0*
0)
bx (
0'
x&
0%
0$
b0 #
b0 "
0!
$end
#5
1%
1)
#10
0%
0)
#15
12
14
b0 (
1&
1+
b111 9
1'
1.
1%
1)
#20
0%
0)
#25
16
1*
b1 5
b10000110000100000100000 7
b10000110000100000100000 ,
b1 (
1%
1)
#30
0%
0)
#35
b10 5
b101001100010000000100001 7
b101001100010000000100001 ,
13
1$
1/
1!
b100 1
b100 #
b10000110000100000100000 0
b10000110000100000100000 "
b10 (
1%
1)
#40
0%
0)
#45
b1000 1
b1000 #
b101001100010000000100001 0
b101001100010000000100001 "
b11 5
b1000010010011100000100010 7
b1000010010011100000100010 ,
b11 (
1%
1)
#50
0%
0)
#55
b100 5
b1000100101000000100011 7
b1000100101000000100011 ,
b1100 1
b1100 #
b1000010010011100000100010 0
b1000010010011100000100010 "
b100 (
1%
1)
#60
0%
0)
#65
b10000 1
b10000 #
b1000100101000000100011 0
b1000100101000000100011 "
b0 5
18
1-
b10000010000010000000001100100 7
b10000010000010000000001100100 ,
b101 (
1%
1)
#70
0%
0)
#75
06
0*
b1 5
08
0-
b10000110000100000100000 7
b10000110000100000100000 ,
02
04
b10100 1
b10100 #
b10000010000010000000001100100 0
b10000010000010000000001100100 "
b110 (
1%
1)
#80
0%
0)
#85
b0 1
b0 #
b0 0
b0 "
0/
0!
03
0$
0&
0+
b111 (
1%
1)
