source/header.vh
`define OPCODE_WIDTH 6
`define RTYPE 0
`define LOAD 1
`define STORE 2
`define BEQ 3
`define ADDI 4
`define ADDIU 5
`define SLTI 6
`define SLTIU 7
`define ANDI 8
`define ORI 9
`define XORI 10
`define BNE 11

`define FUNCT_WIDTH 6
`define ADD 6'b100000
`define SUB 6'b100001
`define AND 6'b100010
`define OR 6'b100011
`define XOR 6'b100100
`define SLT 6'b100101
`define SLTU 6'b100110
`define SLL 6'b100111
`define SRL 6'b101000
`define SRA 6'b101001
`define EQ 6'b101010
`define NEQ 6'b101011
`define GE 6'b101100
`define GEU 6'b101101
`define ADDU 6'b101110

`define DWIDTH 32
`define IWIDTH 32
`define AWIDTH 5
`define PC_WIDTH 32
`define AWIDTH_MEM 32
`define IMM_WIDTH 16
`define DEPTH 5

source/transmit.v
`ifndef TRANSMIT_V
`define TRANSMIT_V
`include "./source/header.vh"
module transmit (
    t_clk, t_rst, t_i_syn, t_o_instr, t_o_last, t_o_ack
);
    input t_clk, t_rst;
    input t_i_syn;
    output reg [`IWIDTH - 1 : 0] t_o_instr;
    output reg t_o_last, t_o_ack;
    integer counter;

    reg [`IWIDTH - 1 : 0] mem_instr [0 : `DEPTH - 1];

    always @(posedge t_clk, negedge t_rst) begin
        if (!t_rst) begin   
            $readmemh("./source/instr.txt", mem_instr, 0, `DEPTH - 1);
            counter <= 0;
            t_o_last <= 1'b0;
            t_o_instr <= {`IWIDTH{1'bz}};
            t_o_ack <= 1'b0;
        end
        else begin
            if (t_i_syn) begin
                t_o_instr <= mem_instr[counter];
                if (`DEPTH == 1) begin
                    t_o_last <= 1'b1;
                end
                else if (`DEPTH > 1) begin
                    t_o_last <= (counter == `DEPTH - 1) ? 1'b1 : 1'b0;
                end
                else begin
                    t_o_last <= 1'b0;
                end
                counter <= (counter < `DEPTH - 1) ? counter + 1 : 0;
                t_o_ack <= 1'b1;
                if (t_o_last) begin
                    t_o_ack <= 1'b0;
                end
            end
            else begin
                t_o_ack <= 1'b0;
                t_o_last <= 1'b0;
            end
        end
    end 
endmodule

`endif

source/instruction_fetch.v
`ifndef INSTRUCTION_FETCH_V
`define INSTRUCTION_FETCH_V
`include "./source/transmit.v"

module instruction_fetch (
    f_clk, f_rst, f_i_ce, f_i_change_pc, f_i_pc, f_o_instr, f_o_pc, f_o_ce
);
    input f_clk, f_rst;
    input f_i_ce;
    input f_i_change_pc;
    input [`PC_WIDTH - 1 : 0] f_i_pc;
    output reg [`IWIDTH - 1 : 0] f_o_instr;
    output reg [`PC_WIDTH - 1 : 0] f_o_pc;
    output reg f_o_ce;
    wire [`IWIDTH - 1 : 0] f_i_instr;
    wire f_i_ack;
    wire f_i_last;
    reg f_o_syn;
    reg [`PC_WIDTH - 1 : 0] cur_pc;
    wire [`PC_WIDTH - 1 : 0] temp_pc;
    transmit t (
        .t_clk(f_clk), 
        .t_rst(f_rst), 
        .t_i_syn(f_o_syn), 
        .t_o_instr(f_i_instr), 
        .t_o_last(f_i_last), 
        .t_o_ack(f_i_ack)
    );
    always@(posedge f_clk, negedge f_rst) begin
        if (!f_rst) begin
            f_o_instr <= {`IWIDTH{1'b0}};
            f_o_pc <= {`PC_WIDTH{1'b0}};
            f_o_syn <= 1'b0;
            f_o_ce <= 1'b0;
            cur_pc <= {`PC_WIDTH{1'b0}};
        end
        else begin
            if (f_i_ce) begin
                // cur_pc <= ;
                f_o_pc <= (f_i_change_pc) ? f_i_pc : f_o_pc + 4;
                f_o_syn <= (f_i_last && f_i_ack) ? 1'b0 : 1'b1;
                if (f_i_ack) begin
                    f_o_instr <= f_i_instr;
                    f_o_ce <= 1'b1;
                end
                else begin
                    f_o_ce <= 1'b0;
                end
            end
            else begin
                f_o_ce <= 1'b0;
                f_o_syn <= 1'b0;
                f_o_instr <= {`IWIDTH{1'b0}};
                f_o_pc <= {`PC_WIDTH{1'b0}};
            end
        end
    end
endmodule
`endif

test/tb_fetch.v
`include "./source/instruction_fetch.v"
module tb;
    parameter IWIDTH = 32;
    parameter PC_WIDTH = 32;
    parameter DEPTH = 6;
    
    reg f_clk, f_rst;
    reg f_i_ce;
    reg f_i_change_pc;
    reg [PC_WIDTH - 1 : 0] f_i_pc;
    wire [IWIDTH - 1 : 0] f_o_instr;
    wire [PC_WIDTH - 1 : 0] f_o_pc; 
    wire f_o_ce;
    integer i;

    instruction_fetch #(
        .IWIDTH(IWIDTH),
        .DEPTH(DEPTH),
        .PC_WIDTH(PC_WIDTH)
    ) f (
        .f_clk(f_clk), 
        .f_rst(f_rst), 
        .f_i_ce(f_i_ce), 
        .f_i_change_pc(f_i_change_pc),
        .f_i_pc(f_i_pc),
        .f_o_instr(f_o_instr), 
        .f_o_pc(f_o_pc),
        .f_o_ce(f_o_ce)
    );

    initial begin
        f_clk = 1'b0;
    end
    always #5 f_clk = ~f_clk;

    initial begin
        $dumpfile("./waveform/fetch.vcd");
        $dumpvars(0, tb);
    end

    task reset (input integer counter);
        begin
            f_rst = 1'b0;
            repeat(counter) @(posedge f_clk);
            f_rst = 1'b1;
        end
    endtask 

    task display (input integer counter);
        begin
            f_i_ce = 1'b1;
            for (i = 0; i < counter; i = i + 1) begin
                @(posedge f_clk);
                $display($time, " ", "instr = %h, pc = %d, last = %b, syn = %b, ack = %b, ce = %b", f_o_instr, f_o_pc, f.f_i_last, f.f_o_syn, f.f_i_ack, f_o_ce); 
            end
            f_i_ce = 1'b0;
        end
    endtask

    initial begin
        reset(2);
        display(9);
        repeat(10) @(posedge f_clk);
        $finish;
    end
endmodule

waveform/fetch.vcd
$date
	Thu Oct 09 08:46:49 2025
$end
$version
	Icarus Verilog
$end
$timescale
	1s
$end
$scope module tb $end
$var wire 1 ! f_o_ce $end
$var wire 32 " f_o_instr [31:0] $end
$var wire 32 # f_o_pc [31:0] $end
$var reg 1 $ f_clk $end
$var reg 1 % f_i_ce $end
$var reg 1 & f_i_change_pc $end
$var reg 32 ' f_i_pc [31:0] $end
$var reg 1 ( f_rst $end
$var integer 32 ) i [31:0] $end
$scope module f $end
$var wire 1 * f_clk $end
$var wire 1 + f_i_ack $end
$var wire 1 , f_i_ce $end
$var wire 1 - f_i_change_pc $end
$var wire 32 . f_i_instr [31:0] $end
$var wire 1 / f_i_last $end
$var wire 32 0 f_i_pc [31:0] $end
$var wire 1 1 f_rst $end
$var wire 32 2 temp_pc [31:0] $end
$var reg 32 3 cur_pc [31:0] $end
$var reg 1 4 f_o_ce $end
$var reg 32 5 f_o_instr [31:0] $end
$var reg 32 6 f_o_pc [31:0] $end
$var reg 1 7 f_o_syn $end
$scope module t $end
$var wire 1 * t_clk $end
$var wire 1 8 t_i_syn $end
$var wire 1 1 t_rst $end
$var integer 32 9 counter [31:0] $end
$var reg 1 : t_o_ack $end
$var reg 32 ; t_o_instr [31:0] $end
$var reg 1 < t_o_last $end
$upscope $end
$upscope $end
$scope task display $end
$var integer 32 = counter [31:0] $end
$upscope $end
$scope task reset $end
$var integer 32 > counter [31:0] $end
$upscope $end
$upscope $end
$enddefinitions $end
#0
$dumpvars
b10 >
bx =
0<
b0 ;
0:
b0 9
08
07
b0 6
b0 5
04
b0 3
bx 2
01
bx 0
0/
b0 .
x-
x,
0+
0*
bx )
0(
bx '
x&
x%
0$
b0 #
b0 "
0!
$end
#5
1$
1*
#10
0$
0*
#15
17
18
b0 )
1%
1,
b1001 =
1(
11
1$
1*
#20
0$
0*
#25
1:
1+
b1 9
b10000110000100000100000 ;
b10000110000100000100000 .
b1 )
1$
1*
#30
0$
0*
#35
b10 9
b101001100010000000100001 ;
b101001100010000000100001 .
14
1!
bx 3
b10000110000100000100000 5
b10000110000100000100000 "
b10 )
1$
1*
#40
0$
0*
#45
bx 6
bx #
b101001100010000000100001 5
b101001100010000000100001 "
b11 9
b1000010010011100000100010 ;
b1000010010011100000100010 .
b11 )
1$
1*
#50
0$
0*
#55
b100 9
b1000100101000000100011 ;
b1000100101000000100011 .
b1000010010011100000100010 5
b1000010010011100000100010 "
b100 )
1$
1*
#60
0$
0*
#65
b1000100101000000100011 5
b1000100101000000100011 "
b101 9
b10000010000010000000001100100 ;
b10000010000010000000001100100 .
b101 )
1$
1*
#70
0$
0*
#75
b0 9
1<
1/
b1101011010110000000000010000 ;
b1101011010110000000000010000 .
b10000010000010000000001100100 5
b10000010000010000000001100100 "
b110 )
1$
1*
#80
0$
0*
#85
b1101011010110000000000010000 5
b1101011010110000000000010000 "
07
08
0:
0+
b1 9
0<
0/
b10000110000100000100000 ;
b10000110000100000100000 .
b111 )
1$
1*
#90
0$
0*
#95
04
0!
17
18
b1000 )
1$
1*
#100
0$
0*
#105
b0 6
b0 #
b0 5
b0 "
07
08
1:
1+
b10 9
b101001100010000000100001 ;
b101001100010000000100001 .
0%
0,
b1001 )
1$
1*
#110
0$
0*
#115
0:
0+
1$
1*
