source/header.vh
`define OPCODE_WIDTH 6
`define RTYPE 0
`define LOAD 1
`define STORE 2
`define BEQ 3
`define ADDI 4
`define ADDIU 5
`define SLTI 6
`define SLTIU 7
`define ANDI 8
`define ORI 9
`define XORI 10
`define BNE 11

`define FUNCT_WIDTH 6
`define ADD 6'b100000
`define SUB 6'b100001
`define AND 6'b100010
`define OR 6'b100011
`define XOR 6'b100100
`define SLT 6'b100101
`define SLTU 6'b100110
`define SLL 6'b100111
`define SRL 6'b101000
`define SRA 6'b101001
`define EQ 6'b101010
`define NEQ 6'b101011
`define GE 6'b101100
`define GEU 6'b101101
`define ADDU 6'b101110

`define DWIDTH 32
`define IWIDTH 32
`define AWIDTH 5
`define PC_WIDTH 32
`define AWIDTH_MEM 32
`define IMM_WIDTH 16
`define DEPTH 5

source/transmit.v
`ifndef TRANSMIT_V
`define TRANSMIT_V
`include "./source/header.vh"
module transmit (
    t_clk, t_rst, t_i_syn, t_o_instr, t_o_last, t_o_ack
);
    input t_clk, t_rst;
    input t_i_syn;
    output reg [`IWIDTH - 1 : 0] t_o_instr;
    output reg t_o_last, t_o_ack;
    integer counter;

    reg [`IWIDTH - 1 : 0] mem_instr [0 : `DEPTH - 1];

    always @(posedge t_clk, negedge t_rst) begin
        if (!t_rst) begin   
            $readmemh("./source/instr.txt", mem_instr, 0, `DEPTH - 1);
            counter <= 0;
            t_o_last <= 1'b0;
            t_o_instr <= {`IWIDTH{1'bz}};
            t_o_ack <= 1'b0;
        end
        else begin
            if (t_i_syn) begin
                t_o_instr <= mem_instr[counter];
                if (`DEPTH == 1) begin
                    t_o_last <= 1'b1;
                end
                else if (`DEPTH > 1) begin
                    t_o_last <= (counter == `DEPTH - 1) ? 1'b1 : 1'b0;
                end
                else begin
                    t_o_last <= 1'b0;
                end
                counter <= (counter < `DEPTH - 1) ? counter + 1 : 0;
                t_o_ack <= 1'b1;
                if (t_o_last) begin
                    t_o_ack <= 1'b0;
                end
            end
            else begin
                t_o_ack <= 1'b0;
                t_o_last <= 1'b0;
            end
        end
    end 
endmodule

`endif

test/tb_transmit.v
`include "./source/transmit.v"
module tb;
    reg t_clk, t_rst;
    reg t_i_syn;
    wire [`IWIDTH - 1 : 0] t_o_instr;
    wire t_o_last, t_o_ack;
    integer i;

    transmit t (
        .t_clk(t_clk), 
        .t_rst(t_rst), 
        .t_i_syn(t_i_syn),
        .t_o_instr(t_o_instr), 
        .t_o_last(t_o_last), 
        .t_o_ack(t_o_ack)
    );
    
    initial begin
        i = 0;
        t_i_syn = 1'b0;
        t_clk = 1'b0;
    end
    always #5 t_clk = ~t_clk;

    initial begin
        $dumpfile("./waveform/transmit.vcd");
        $dumpvars(0, tb);
    end

    task reset (input integer counter);
        begin
            t_rst = 1'b0;
            repeat(counter) @(posedge t_clk);
            t_rst = 1'b1;
        end
    endtask

    task display (input integer counter);
        begin
            t_i_syn = 1'b1;
            for (i = 0; i < counter; i = i + 1) begin
                @(posedge t_clk);
                $display($time, " ", "instr = %h, last = %b, ack = %b", t_o_instr, t_o_last, t_o_ack);
            end
            t_i_syn = 1'b0;
            @(posedge t_clk);
        end
    endtask

    initial begin
        reset(2);
        @(posedge t_clk);
        display(7);
        #40; $finish;
    end
endmodule

waveform/transmit.vcd
$date
	Thu Oct 09 08:46:09 2025
$end
$version
	Icarus Verilog
$end
$timescale
	1s
$end
$scope module tb $end
$var wire 1 ! t_o_ack $end
$var wire 32 " t_o_instr [31:0] $end
$var wire 1 # t_o_last $end
$var integer 32 $ i [31:0] $end
$var reg 1 % t_clk $end
$var reg 1 & t_i_syn $end
$var reg 1 ' t_rst $end
$scope module t $end
$var wire 1 ( t_clk $end
$var wire 1 ) t_i_syn $end
$var wire 1 * t_rst $end
$var integer 32 + counter [31:0] $end
$var reg 1 , t_o_ack $end
$var reg 32 - t_o_instr [31:0] $end
$var reg 1 . t_o_last $end
$upscope $end
$scope task display $end
$var integer 32 / counter [31:0] $end
$upscope $end
$scope task reset $end
$var integer 32 0 counter [31:0] $end
$upscope $end
$upscope $end
$enddefinitions $end
#0
$dumpvars
b10 0
bx /
0.
b0 -
0,
b0 +
0*
0)
0(
0'
0&
0%
b0 $
0#
b0 "
0!
$end
#5
1%
1(
#10
0%
0(
#15
1'
1*
1%
1(
#20
0%
0(
#25
1,
1!
b1 +
b10000110000100000100000 -
b10000110000100000100000 "
1&
1)
b111 /
1%
1(
#30
0%
0(
#35
b10 +
b101001100010000000100001 -
b101001100010000000100001 "
b1 $
1%
1(
#40
0%
0(
#45
b11 +
b1000010010011100000100010 -
b1000010010011100000100010 "
b10 $
1%
1(
#50
0%
0(
#55
b100 +
b1000100101000000100011 -
b1000100101000000100011 "
b11 $
1%
1(
#60
0%
0(
#65
b101 +
b10000010000010000000001100100 -
b10000010000010000000001100100 "
b100 $
1%
1(
#70
0%
0(
#75
b0 +
1.
1#
b1101011010110000000000010000 -
b1101011010110000000000010000 "
b101 $
1%
1(
#80
0%
0(
#85
0,
0!
b1 +
0.
0#
b10000110000100000100000 -
b10000110000100000100000 "
b110 $
1%
1(
#90
0%
0(
#95
0&
0)
b111 $
1%
1(
